jupyter_export_html_style/__init__.py
jupyter_export_html_style/preprocessor.py
jupyter_export_html_style/py.typed
jupyter_export_html_style/exporters/__init__.py
jupyter_export_html_style/exporters/html.py
jupyter_export_html_style/exporters/slides.py
jupyter_export_html_style/exporters/webpdf.py
jupyter_export_html_style/templates/styled/base.html.j2
jupyter_export_html_style/templates/styled/conf.json
jupyter_export_html_style/templates/styled/index.html.j2
jupyter_export_html_style/templates/styled_reveal/base.html.j2
jupyter_export_html_style/templates/styled_reveal/conf.json
jupyter_export_html_style/templates/styled_reveal/index.html.j2
jupyter_export_html_style/templates/webpdf/base.html.j2
jupyter_export_html_style/templates/webpdf/conf.json
jupyter_export_html_style/templates/webpdf/index.html.j2
jupyter_export_html_style-0.1.1.dist-info/licenses/LICENSE
jupyter_export_html_style-0.1.1.dist-info/METADATA
jupyter_export_html_style-0.1.1.dist-info/WHEEL
jupyter_export_html_style-0.1.1.dist-info/entry_points.txt
jupyter_export_html_style-0.1.1.dist-info/top_level.txt
jupyter_export_html_style-0.1.1.dist-info/RECORD
