Metadata-Version: 2.4
Name: jupyter-export-html-style
Version: 0.1.1
Summary: A JupyterLab extension and nbconvert preprocessor/exporter for HTML export with cell style metadata overrides
Author-email: Gavin Burnell <gavin.burnell@example.com>
License-Expression: MIT
Project-URL: Homepage, https://github.com/gb119/jupyter_export_html_style
Project-URL: Documentation, https://gb119.github.io/jupyter_export_html_style/
Project-URL: Repository, https://github.com/gb119/jupyter_export_html_style
Project-URL: Bug Tracker, https://github.com/gb119/jupyter_export_html_style/issues
Keywords: jupyter,jupyterlab,nbconvert,html,export,notebook
Classifier: Development Status :: 3 - Alpha
Classifier: Framework :: Jupyter
Classifier: Framework :: Jupyter :: JupyterLab
Classifier: Framework :: Jupyter :: JupyterLab :: 4
Classifier: Intended Audience :: Developers
Classifier: Intended Audience :: Science/Research
Classifier: Programming Language :: Python :: 3
Classifier: Programming Language :: Python :: 3.11
Classifier: Programming Language :: Python :: 3.12
Classifier: Programming Language :: Python :: 3.13
Classifier: Topic :: Software Development :: Libraries :: Python Modules
Requires-Python: >=3.11
License-File: LICENSE
Requires-Dist: nbconvert>=6.0.0
Requires-Dist: traitlets>=5.0.0
Requires-Dist: jupyter-core>=4.7.0
Provides-Extra: dev
Requires-Dist: pytest>=7.0.0; extra == "dev"
Requires-Dist: pytest-cov>=4.0.0; extra == "dev"
Requires-Dist: black>=23.0.0; extra == "dev"
Requires-Dist: ruff>=0.1.0; extra == "dev"
Requires-Dist: mypy>=1.0.0; extra == "dev"
Provides-Extra: docs
Requires-Dist: sphinx>=5.0.0; extra == "docs"
Requires-Dist: sphinx-rtd-theme>=1.0.0; extra == "docs"
Requires-Dist: myst-parser>=0.18.0; extra == "docs"
Provides-Extra: jupyterlab
Requires-Dist: jupyterlab>=4.0.0; extra == "jupyterlab"
Dynamic: license-file
